src/__init__.py
src/send_logs.py
logmi_iswearican-0.0.1.dist-info/METADATA
logmi_iswearican-0.0.1.dist-info/WHEEL
logmi_iswearican-0.0.1.dist-info/licenses/LICENSE
logmi_iswearican-0.0.1.dist-info/RECORD
